{"version":1,"locale":"ar-ae","generatedAt":"2026-06-02T21:04:25.085Z","global":{"collections":[{"slug":"alfa","value":"alfa","label":"ألفا نتورك","depth":0,"count":1},{"slug":"alfa-antennas","value":"alfa-antennas","label":"Antennas","depth":1,"count":1},{"slug":"mikrotik","value":"mikrotik","label":"MikroTik","depth":0,"count":1},{"slug":"mikrotik-60ghz-wireless","value":"mikrotik-60ghz-wireless","label":"60GHz Wireless","depth":1,"count":1},{"slug":"mikrotik-60ghz-antennas","value":"mikrotik-60ghz-antennas","label":"60GHz antennas","depth":2,"count":1},{"slug":"mikrotik-antennas","value":"mikrotik-antennas","label":"Antennas","depth":1,"count":1},{"slug":"mikrotik-iot-products","value":"mikrotik-iot-products","label":"IoT Products","depth":1,"count":1},{"slug":"mikrotik-iot-antennas","value":"mikrotik-iot-antennas","label":"Antennas","depth":2,"count":1},{"slug":"mikrotik-wireless-systems","value":"mikrotik-wireless-systems","label":"Wireless Systems","depth":1,"count":1},{"slug":"mikrotik-lhg-antennas","value":"mikrotik-lhg-antennas","label":"LHG antennas","depth":2,"count":1},{"slug":"mikrotik-sxt-antennas","value":"mikrotik-sxt-antennas","label":"SXT antennas","depth":2,"count":1},{"slug":"ubiquiti","value":"ubiquiti","label":"Ubiquiti","depth":0,"count":2},{"slug":"ubiquiti-outdoor-wireless","value":"ubiquiti-outdoor-wireless","label":"Outdoor Wireless","depth":1,"count":2},{"slug":"ubiquiti-outdoor-antennas","value":"ubiquiti-outdoor-antennas","label":"Outdoor Antennas","depth":2,"count":1}],"categories":[{"value":"Carrier Backhaul Radio","label":"Carrier Backhaul Radio","count":1},{"value":"Integrated Antennas","label":"Integrated Antennas","count":1}],"brands":[{"value":"MikroTik","label":"MikroTik","count":1},{"value":"Ubiquiti","label":"Ubiquiti","count":1}],"tags":[{"value":"60GHz antennas","label":"60GHz antennas","count":1},{"value":"60GHz Wireless","label":"60GHz Wireless","count":1},{"value":"ألفا نتورك","label":"ألفا نتورك","count":1},{"value":"Antennas","label":"Antennas","count":1},{"value":"Carrier Backhaul Radio","label":"Carrier Backhaul Radio","count":1},{"value":"Integrated Antennas","label":"Integrated Antennas","count":1},{"value":"IoT Products","label":"IoT Products","count":1},{"value":"LHG antennas","label":"LHG antennas","count":1},{"value":"MikroTik","label":"MikroTik","count":1},{"value":"Outdoor Antennas","label":"Outdoor Antennas","count":1},{"value":"Outdoor Wireless","label":"Outdoor Wireless","count":2},{"value":"SXT antennas","label":"SXT antennas","count":1},{"value":"Ubiquiti","label":"Ubiquiti","count":2},{"value":"Wireless Systems","label":"Wireless Systems","count":1}],"conditions":[{"value":"new","label":"new","count":2},{"value":"used","label":"used","count":1}],"variations":{"Plug":[{"value":"EU","label":"EU","count":1},{"value":"UK","label":"UK","count":1},{"value":"US","label":"US","count":1}]},"priceMin":159.25,"priceMax":303.78,"currency":"USD"},"byCollection":{"ubiquiti":{"categories":[{"value":"Carrier Backhaul Radio","label":"Carrier Backhaul Radio","count":1},{"value":"Integrated Antennas","label":"Integrated Antennas","count":1}],"brands":[{"value":"MikroTik","label":"MikroTik","count":1},{"value":"Ubiquiti","label":"Ubiquiti","count":1}],"tags":[{"value":"60GHz antennas","label":"60GHz antennas","count":1},{"value":"60GHz Wireless","label":"60GHz Wireless","count":1},{"value":"ألفا نتورك","label":"ألفا نتورك","count":1},{"value":"Antennas","label":"Antennas","count":1},{"value":"Carrier Backhaul Radio","label":"Carrier Backhaul Radio","count":1},{"value":"Integrated Antennas","label":"Integrated Antennas","count":1},{"value":"IoT Products","label":"IoT Products","count":1},{"value":"LHG antennas","label":"LHG antennas","count":1},{"value":"MikroTik","label":"MikroTik","count":1},{"value":"Outdoor Antennas","label":"Outdoor Antennas","count":1},{"value":"Outdoor Wireless","label":"Outdoor Wireless","count":2},{"value":"SXT antennas","label":"SXT antennas","count":1},{"value":"Ubiquiti","label":"Ubiquiti","count":2},{"value":"Wireless Systems","label":"Wireless Systems","count":1}],"conditions":[{"value":"new","label":"new","count":2},{"value":"used","label":"used","count":1}],"variations":{"Plug":[{"value":"EU","label":"EU","count":1},{"value":"UK","label":"UK","count":1},{"value":"US","label":"US","count":1}]},"priceMin":159.25,"priceMax":303.78,"currency":"USD"},"ubiquiti-outdoor-wireless":{"categories":[{"value":"Carrier Backhaul Radio","label":"Carrier Backhaul Radio","count":1},{"value":"Integrated Antennas","label":"Integrated Antennas","count":1}],"brands":[{"value":"MikroTik","label":"MikroTik","count":1},{"value":"Ubiquiti","label":"Ubiquiti","count":1}],"tags":[{"value":"60GHz antennas","label":"60GHz antennas","count":1},{"value":"60GHz Wireless","label":"60GHz Wireless","count":1},{"value":"ألفا نتورك","label":"ألفا نتورك","count":1},{"value":"Antennas","label":"Antennas","count":1},{"value":"Carrier Backhaul Radio","label":"Carrier Backhaul Radio","count":1},{"value":"Integrated Antennas","label":"Integrated Antennas","count":1},{"value":"IoT Products","label":"IoT Products","count":1},{"value":"LHG antennas","label":"LHG antennas","count":1},{"value":"MikroTik","label":"MikroTik","count":1},{"value":"Outdoor Antennas","label":"Outdoor Antennas","count":1},{"value":"Outdoor Wireless","label":"Outdoor Wireless","count":2},{"value":"SXT antennas","label":"SXT antennas","count":1},{"value":"Ubiquiti","label":"Ubiquiti","count":2},{"value":"Wireless Systems","label":"Wireless Systems","count":1}],"conditions":[{"value":"new","label":"new","count":2},{"value":"used","label":"used","count":1}],"variations":{"Plug":[{"value":"EU","label":"EU","count":1},{"value":"UK","label":"UK","count":1},{"value":"US","label":"US","count":1}]},"priceMin":159.25,"priceMax":303.78,"currency":"USD"},"alfa":{"categories":[{"value":"Integrated Antennas","label":"Integrated Antennas","count":1}],"brands":[{"value":"MikroTik","label":"MikroTik","count":1}],"tags":[{"value":"60GHz antennas","label":"60GHz antennas","count":1},{"value":"60GHz Wireless","label":"60GHz Wireless","count":1},{"value":"ألفا نتورك","label":"ألفا نتورك","count":1},{"value":"Antennas","label":"Antennas","count":1},{"value":"Integrated Antennas","label":"Integrated Antennas","count":1},{"value":"IoT Products","label":"IoT Products","count":1},{"value":"LHG antennas","label":"LHG antennas","count":1},{"value":"MikroTik","label":"MikroTik","count":1},{"value":"Outdoor Antennas","label":"Outdoor Antennas","count":1},{"value":"Outdoor Wireless","label":"Outdoor Wireless","count":1},{"value":"SXT antennas","label":"SXT antennas","count":1},{"value":"Ubiquiti","label":"Ubiquiti","count":1},{"value":"Wireless Systems","label":"Wireless Systems","count":1}],"conditions":[{"value":"new","label":"new","count":1},{"value":"used","label":"used","count":1}],"variations":{"Plug":[{"value":"EU","label":"EU","count":1},{"value":"UK","label":"UK","count":1},{"value":"US","label":"US","count":1}]},"priceMin":159.25,"priceMax":159.25,"currency":"USD"},"alfa-antennas":{"categories":[{"value":"Integrated Antennas","label":"Integrated Antennas","count":1}],"brands":[{"value":"MikroTik","label":"MikroTik","count":1}],"tags":[{"value":"60GHz antennas","label":"60GHz antennas","count":1},{"value":"60GHz Wireless","label":"60GHz Wireless","count":1},{"value":"ألفا نتورك","label":"ألفا نتورك","count":1},{"value":"Antennas","label":"Antennas","count":1},{"value":"Integrated Antennas","label":"Integrated Antennas","count":1},{"value":"IoT Products","label":"IoT Products","count":1},{"value":"LHG antennas","label":"LHG antennas","count":1},{"value":"MikroTik","label":"MikroTik","count":1},{"value":"Outdoor Antennas","label":"Outdoor Antennas","count":1},{"value":"Outdoor Wireless","label":"Outdoor Wireless","count":1},{"value":"SXT antennas","label":"SXT antennas","count":1},{"value":"Ubiquiti","label":"Ubiquiti","count":1},{"value":"Wireless Systems","label":"Wireless Systems","count":1}],"conditions":[{"value":"new","label":"new","count":1},{"value":"used","label":"used","count":1}],"variations":{"Plug":[{"value":"EU","label":"EU","count":1},{"value":"UK","label":"UK","count":1},{"value":"US","label":"US","count":1}]},"priceMin":159.25,"priceMax":159.25,"currency":"USD"},"mikrotik":{"categories":[{"value":"Integrated Antennas","label":"Integrated Antennas","count":1}],"brands":[{"value":"MikroTik","label":"MikroTik","count":1}],"tags":[{"value":"60GHz antennas","label":"60GHz antennas","count":1},{"value":"60GHz Wireless","label":"60GHz Wireless","count":1},{"value":"ألفا نتورك","label":"ألفا نتورك","count":1},{"value":"Antennas","label":"Antennas","count":1},{"value":"Integrated Antennas","label":"Integrated Antennas","count":1},{"value":"IoT Products","label":"IoT Products","count":1},{"value":"LHG antennas","label":"LHG antennas","count":1},{"value":"MikroTik","label":"MikroTik","count":1},{"value":"Outdoor Antennas","label":"Outdoor Antennas","count":1},{"value":"Outdoor Wireless","label":"Outdoor Wireless","count":1},{"value":"SXT antennas","label":"SXT antennas","count":1},{"value":"Ubiquiti","label":"Ubiquiti","count":1},{"value":"Wireless Systems","label":"Wireless Systems","count":1}],"conditions":[{"value":"new","label":"new","count":1},{"value":"used","label":"used","count":1}],"variations":{"Plug":[{"value":"EU","label":"EU","count":1},{"value":"UK","label":"UK","count":1},{"value":"US","label":"US","count":1}]},"priceMin":159.25,"priceMax":159.25,"currency":"USD"},"mikrotik-60ghz-wireless":{"categories":[{"value":"Integrated Antennas","label":"Integrated Antennas","count":1}],"brands":[{"value":"MikroTik","label":"MikroTik","count":1}],"tags":[{"value":"60GHz antennas","label":"60GHz antennas","count":1},{"value":"60GHz Wireless","label":"60GHz Wireless","count":1},{"value":"ألفا نتورك","label":"ألفا نتورك","count":1},{"value":"Antennas","label":"Antennas","count":1},{"value":"Integrated Antennas","label":"Integrated Antennas","count":1},{"value":"IoT Products","label":"IoT Products","count":1},{"value":"LHG antennas","label":"LHG antennas","count":1},{"value":"MikroTik","label":"MikroTik","count":1},{"value":"Outdoor Antennas","label":"Outdoor Antennas","count":1},{"value":"Outdoor Wireless","label":"Outdoor Wireless","count":1},{"value":"SXT antennas","label":"SXT antennas","count":1},{"value":"Ubiquiti","label":"Ubiquiti","count":1},{"value":"Wireless Systems","label":"Wireless Systems","count":1}],"conditions":[{"value":"new","label":"new","count":1},{"value":"used","label":"used","count":1}],"variations":{"Plug":[{"value":"EU","label":"EU","count":1},{"value":"UK","label":"UK","count":1},{"value":"US","label":"US","count":1}]},"priceMin":159.25,"priceMax":159.25,"currency":"USD"},"mikrotik-60ghz-antennas":{"categories":[{"value":"Integrated Antennas","label":"Integrated Antennas","count":1}],"brands":[{"value":"MikroTik","label":"MikroTik","count":1}],"tags":[{"value":"60GHz antennas","label":"60GHz antennas","count":1},{"value":"60GHz Wireless","label":"60GHz Wireless","count":1},{"value":"ألفا نتورك","label":"ألفا نتورك","count":1},{"value":"Antennas","label":"Antennas","count":1},{"value":"Integrated Antennas","label":"Integrated Antennas","count":1},{"value":"IoT Products","label":"IoT Products","count":1},{"value":"LHG antennas","label":"LHG antennas","count":1},{"value":"MikroTik","label":"MikroTik","count":1},{"value":"Outdoor Antennas","label":"Outdoor Antennas","count":1},{"value":"Outdoor Wireless","label":"Outdoor Wireless","count":1},{"value":"SXT antennas","label":"SXT antennas","count":1},{"value":"Ubiquiti","label":"Ubiquiti","count":1},{"value":"Wireless Systems","label":"Wireless Systems","count":1}],"conditions":[{"value":"new","label":"new","count":1},{"value":"used","label":"used","count":1}],"variations":{"Plug":[{"value":"EU","label":"EU","count":1},{"value":"UK","label":"UK","count":1},{"value":"US","label":"US","count":1}]},"priceMin":159.25,"priceMax":159.25,"currency":"USD"},"mikrotik-antennas":{"categories":[{"value":"Integrated Antennas","label":"Integrated Antennas","count":1}],"brands":[{"value":"MikroTik","label":"MikroTik","count":1}],"tags":[{"value":"60GHz antennas","label":"60GHz antennas","count":1},{"value":"60GHz Wireless","label":"60GHz Wireless","count":1},{"value":"ألفا نتورك","label":"ألفا نتورك","count":1},{"value":"Antennas","label":"Antennas","count":1},{"value":"Integrated Antennas","label":"Integrated Antennas","count":1},{"value":"IoT Products","label":"IoT Products","count":1},{"value":"LHG antennas","label":"LHG antennas","count":1},{"value":"MikroTik","label":"MikroTik","count":1},{"value":"Outdoor Antennas","label":"Outdoor Antennas","count":1},{"value":"Outdoor Wireless","label":"Outdoor Wireless","count":1},{"value":"SXT antennas","label":"SXT antennas","count":1},{"value":"Ubiquiti","label":"Ubiquiti","count":1},{"value":"Wireless Systems","label":"Wireless Systems","count":1}],"conditions":[{"value":"new","label":"new","count":1},{"value":"used","label":"used","count":1}],"variations":{"Plug":[{"value":"EU","label":"EU","count":1},{"value":"UK","label":"UK","count":1},{"value":"US","label":"US","count":1}]},"priceMin":159.25,"priceMax":159.25,"currency":"USD"},"mikrotik-iot-products":{"categories":[{"value":"Integrated Antennas","label":"Integrated Antennas","count":1}],"brands":[{"value":"MikroTik","label":"MikroTik","count":1}],"tags":[{"value":"60GHz antennas","label":"60GHz antennas","count":1},{"value":"60GHz Wireless","label":"60GHz Wireless","count":1},{"value":"ألفا نتورك","label":"ألفا نتورك","count":1},{"value":"Antennas","label":"Antennas","count":1},{"value":"Integrated Antennas","label":"Integrated Antennas","count":1},{"value":"IoT Products","label":"IoT Products","count":1},{"value":"LHG antennas","label":"LHG antennas","count":1},{"value":"MikroTik","label":"MikroTik","count":1},{"value":"Outdoor Antennas","label":"Outdoor Antennas","count":1},{"value":"Outdoor Wireless","label":"Outdoor Wireless","count":1},{"value":"SXT antennas","label":"SXT antennas","count":1},{"value":"Ubiquiti","label":"Ubiquiti","count":1},{"value":"Wireless Systems","label":"Wireless Systems","count":1}],"conditions":[{"value":"new","label":"new","count":1},{"value":"used","label":"used","count":1}],"variations":{"Plug":[{"value":"EU","label":"EU","count":1},{"value":"UK","label":"UK","count":1},{"value":"US","label":"US","count":1}]},"priceMin":159.25,"priceMax":159.25,"currency":"USD"},"mikrotik-iot-antennas":{"categories":[{"value":"Integrated Antennas","label":"Integrated Antennas","count":1}],"brands":[{"value":"MikroTik","label":"MikroTik","count":1}],"tags":[{"value":"60GHz antennas","label":"60GHz antennas","count":1},{"value":"60GHz Wireless","label":"60GHz Wireless","count":1},{"value":"ألفا نتورك","label":"ألفا نتورك","count":1},{"value":"Antennas","label":"Antennas","count":1},{"value":"Integrated Antennas","label":"Integrated Antennas","count":1},{"value":"IoT Products","label":"IoT Products","count":1},{"value":"LHG antennas","label":"LHG antennas","count":1},{"value":"MikroTik","label":"MikroTik","count":1},{"value":"Outdoor Antennas","label":"Outdoor Antennas","count":1},{"value":"Outdoor Wireless","label":"Outdoor Wireless","count":1},{"value":"SXT antennas","label":"SXT antennas","count":1},{"value":"Ubiquiti","label":"Ubiquiti","count":1},{"value":"Wireless Systems","label":"Wireless Systems","count":1}],"conditions":[{"value":"new","label":"new","count":1},{"value":"used","label":"used","count":1}],"variations":{"Plug":[{"value":"EU","label":"EU","count":1},{"value":"UK","label":"UK","count":1},{"value":"US","label":"US","count":1}]},"priceMin":159.25,"priceMax":159.25,"currency":"USD"},"mikrotik-wireless-systems":{"categories":[{"value":"Integrated Antennas","label":"Integrated Antennas","count":1}],"brands":[{"value":"MikroTik","label":"MikroTik","count":1}],"tags":[{"value":"60GHz antennas","label":"60GHz antennas","count":1},{"value":"60GHz Wireless","label":"60GHz Wireless","count":1},{"value":"ألفا نتورك","label":"ألفا نتورك","count":1},{"value":"Antennas","label":"Antennas","count":1},{"value":"Integrated Antennas","label":"Integrated Antennas","count":1},{"value":"IoT Products","label":"IoT Products","count":1},{"value":"LHG antennas","label":"LHG antennas","count":1},{"value":"MikroTik","label":"MikroTik","count":1},{"value":"Outdoor Antennas","label":"Outdoor Antennas","count":1},{"value":"Outdoor Wireless","label":"Outdoor Wireless","count":1},{"value":"SXT antennas","label":"SXT antennas","count":1},{"value":"Ubiquiti","label":"Ubiquiti","count":1},{"value":"Wireless Systems","label":"Wireless Systems","count":1}],"conditions":[{"value":"new","label":"new","count":1},{"value":"used","label":"used","count":1}],"variations":{"Plug":[{"value":"EU","label":"EU","count":1},{"value":"UK","label":"UK","count":1},{"value":"US","label":"US","count":1}]},"priceMin":159.25,"priceMax":159.25,"currency":"USD"},"mikrotik-lhg-antennas":{"categories":[{"value":"Integrated Antennas","label":"Integrated Antennas","count":1}],"brands":[{"value":"MikroTik","label":"MikroTik","count":1}],"tags":[{"value":"60GHz antennas","label":"60GHz antennas","count":1},{"value":"60GHz Wireless","label":"60GHz Wireless","count":1},{"value":"ألفا نتورك","label":"ألفا نتورك","count":1},{"value":"Antennas","label":"Antennas","count":1},{"value":"Integrated Antennas","label":"Integrated Antennas","count":1},{"value":"IoT Products","label":"IoT Products","count":1},{"value":"LHG antennas","label":"LHG antennas","count":1},{"value":"MikroTik","label":"MikroTik","count":1},{"value":"Outdoor Antennas","label":"Outdoor Antennas","count":1},{"value":"Outdoor Wireless","label":"Outdoor Wireless","count":1},{"value":"SXT antennas","label":"SXT antennas","count":1},{"value":"Ubiquiti","label":"Ubiquiti","count":1},{"value":"Wireless Systems","label":"Wireless Systems","count":1}],"conditions":[{"value":"new","label":"new","count":1},{"value":"used","label":"used","count":1}],"variations":{"Plug":[{"value":"EU","label":"EU","count":1},{"value":"UK","label":"UK","count":1},{"value":"US","label":"US","count":1}]},"priceMin":159.25,"priceMax":159.25,"currency":"USD"},"mikrotik-sxt-antennas":{"categories":[{"value":"Integrated Antennas","label":"Integrated Antennas","count":1}],"brands":[{"value":"MikroTik","label":"MikroTik","count":1}],"tags":[{"value":"60GHz antennas","label":"60GHz antennas","count":1},{"value":"60GHz Wireless","label":"60GHz Wireless","count":1},{"value":"ألفا نتورك","label":"ألفا نتورك","count":1},{"value":"Antennas","label":"Antennas","count":1},{"value":"Integrated Antennas","label":"Integrated Antennas","count":1},{"value":"IoT Products","label":"IoT Products","count":1},{"value":"LHG antennas","label":"LHG antennas","count":1},{"value":"MikroTik","label":"MikroTik","count":1},{"value":"Outdoor Antennas","label":"Outdoor Antennas","count":1},{"value":"Outdoor Wireless","label":"Outdoor Wireless","count":1},{"value":"SXT antennas","label":"SXT antennas","count":1},{"value":"Ubiquiti","label":"Ubiquiti","count":1},{"value":"Wireless Systems","label":"Wireless Systems","count":1}],"conditions":[{"value":"new","label":"new","count":1},{"value":"used","label":"used","count":1}],"variations":{"Plug":[{"value":"EU","label":"EU","count":1},{"value":"UK","label":"UK","count":1},{"value":"US","label":"US","count":1}]},"priceMin":159.25,"priceMax":159.25,"currency":"USD"},"ubiquiti-outdoor-antennas":{"categories":[{"value":"Integrated Antennas","label":"Integrated Antennas","count":1}],"brands":[{"value":"MikroTik","label":"MikroTik","count":1}],"tags":[{"value":"60GHz antennas","label":"60GHz antennas","count":1},{"value":"60GHz Wireless","label":"60GHz Wireless","count":1},{"value":"ألفا نتورك","label":"ألفا نتورك","count":1},{"value":"Antennas","label":"Antennas","count":1},{"value":"Integrated Antennas","label":"Integrated Antennas","count":1},{"value":"IoT Products","label":"IoT Products","count":1},{"value":"LHG antennas","label":"LHG antennas","count":1},{"value":"MikroTik","label":"MikroTik","count":1},{"value":"Outdoor Antennas","label":"Outdoor Antennas","count":1},{"value":"Outdoor Wireless","label":"Outdoor Wireless","count":1},{"value":"SXT antennas","label":"SXT antennas","count":1},{"value":"Ubiquiti","label":"Ubiquiti","count":1},{"value":"Wireless Systems","label":"Wireless Systems","count":1}],"conditions":[{"value":"new","label":"new","count":1},{"value":"used","label":"used","count":1}],"variations":{"Plug":[{"value":"EU","label":"EU","count":1},{"value":"UK","label":"UK","count":1},{"value":"US","label":"US","count":1}]},"priceMin":159.25,"priceMax":159.25,"currency":"USD"}}}